locator_parser/__init__.py
locator_parser/acl.py
locator_parser/actions.py
locator_parser/common.py
locator_parser/io.py
locator_parser/locator.py
onetick/__init__.py
onetick/doc_utilities/__init__.py
onetick/doc_utilities/napoleon.py
onetick/doc_utilities/ot_doctest.py
onetick/doc_utilities/snippets.py
onetick/lib/__init__.py
onetick/lib/instance.py
onetick/py/__init__.py
onetick/py/_stack_info.py
onetick/py/_version.py
onetick/py/backports.py
onetick/py/cache.py
onetick/py/compatibility.py
onetick/py/configuration.py
onetick/py/functions.py
onetick/py/license.py
onetick/py/log.py
onetick/py/math.py
onetick/py/misc.py
onetick/py/otq.py
onetick/py/pyomd_mock.py
onetick/py/run.py
onetick/py/servers.py
onetick/py/session.py
onetick/py/sql.py
onetick/py/state.py
onetick/py/types.py
onetick/py/aggregations/__init__.py
onetick/py/aggregations/_base.py
onetick/py/aggregations/_docs.py
onetick/py/aggregations/compute.py
onetick/py/aggregations/functions.py
onetick/py/aggregations/generic.py
onetick/py/aggregations/high_low.py
onetick/py/aggregations/num_distinct.py
onetick/py/aggregations/order_book.py
onetick/py/aggregations/other.py
onetick/py/callback/__init__.py
onetick/py/callback/callback.py
onetick/py/callback/callbacks.py
onetick/py/core/__init__.py
onetick/py/core/_csv_inspector.py
onetick/py/core/column.py
onetick/py/core/cut_builder.py
onetick/py/core/db_constants.py
onetick/py/core/eval_query.py
onetick/py/core/lambda_object.py
onetick/py/core/multi_output_source.py
onetick/py/core/per_tick_script.py
onetick/py/core/query_inspector.py
onetick/py/core/source.py
onetick/py/core/_internal/__init__.py
onetick/py/core/_internal/_manually_bound_value.py
onetick/py/core/_internal/_nodes_history.py
onetick/py/core/_internal/_proxy_node.py
onetick/py/core/_internal/_state_objects.py
onetick/py/core/_internal/_state_vars.py
onetick/py/core/_internal/_op_utils/__init__.py
onetick/py/core/_internal/_op_utils/every_operand.py
onetick/py/core/_internal/_op_utils/is_const.py
onetick_py-1.183.0.dist-info/licenses/LICENSE
onetick_py-1.183.0.dist-info/METADATA
onetick_py-1.183.0.dist-info/WHEEL
onetick_py-1.183.0.dist-info/entry_points.txt
onetick_py-1.183.0.dist-info/top_level.txt
onetick_py-1.183.0.dist-info/RECORD
