Metadata-Version: 2.4
Name: onetick-py
Version: 1.183.0
Summary: Python package that allows you to work with OneTick
Author-email: solutions <solutions@onetick.com>
License-Expression: MIT
Project-URL: Documentation, https://docs.pip.distribution.sol.onetick.com
Project-URL: OneTick, https://onetick.com
Project-URL: GitHub, https://github.com/onemarketdata/onetick-py
Project-URL: Issues, https://github.com/onemarketdata/onetick-py/issues
Classifier: Topic :: Database :: Front-Ends
Classifier: Topic :: Scientific/Engineering
Classifier: Programming Language :: Python :: 3.9
Classifier: Programming Language :: Python :: 3.10
Classifier: Programming Language :: Python :: 3.11
Classifier: Programming Language :: Python :: 3.12
Classifier: Programming Language :: Python :: 3.13
Classifier: Operating System :: OS Independent
Classifier: Environment :: Console
Requires-Python: >=3.9
License-File: LICENSE
Requires-Dist: pandas>=1.5.2
Requires-Dist: numpy
Requires-Dist: coolname
Requires-Dist: python-dateutil
Requires-Dist: python-dotenv
Requires-Dist: tzlocal
Requires-Dist: tzdata
Requires-Dist: graphviz==0.20.1; python_version > "3.6"
Requires-Dist: packaging>=21.0
Provides-Extra: strict
Requires-Dist: numpy==1.23.0; python_version == "3.9" and extra == "strict"
Requires-Dist: numpy==1.23.0; python_version == "3.10" and extra == "strict"
Requires-Dist: numpy==1.26.4; python_version == "3.11" and extra == "strict"
Requires-Dist: numpy==1.26.4; python_version == "3.12" and extra == "strict"
Requires-Dist: pandas==1.5.2; python_version == "3.9" and extra == "strict"
Requires-Dist: pandas==1.5.3; python_version == "3.10" and extra == "strict"
Requires-Dist: pandas==1.5.3; python_version == "3.11" and extra == "strict"
Requires-Dist: pandas==2.2.1; python_version == "3.12" and extra == "strict"
Requires-Dist: pandas==2.3.0; python_version == "3.13" and extra == "strict"
Requires-Dist: pandas==2.3.3; python_version == "3.14" and extra == "strict"
Provides-Extra: webapi
Requires-Dist: onetick.query_webapi; extra == "webapi"
Provides-Extra: polars
Requires-Dist: polars==1.12.0; extra == "polars"
Dynamic: license-file
Dynamic: provides-extra
Dynamic: requires-dist
